onegov.agency-1.12.0-py3.6-nspkg.pth
onegov/agency/.gitignore
onegov/agency/__init__.py
onegov/agency/app.py
onegov/agency/cli.py
onegov/agency/custom.py
onegov/agency/initial_content.py
onegov/agency/path.py
onegov/agency/pdf.py
onegov/agency/upgrade.py
onegov/agency/assets/js/people-select.js
onegov/agency/assets/js/sortable-multi-checkbox.js
onegov/agency/collections/__init__.py
onegov/agency/collections/agencies.py
onegov/agency/collections/people.py
onegov/agency/content/de.yaml
onegov/agency/forms/__init__.py
onegov/agency/forms/agency.py
onegov/agency/forms/membership.py
onegov/agency/forms/mutation.py
onegov/agency/layouts/__init__.py
onegov/agency/layouts/agency.py
onegov/agency/layouts/membership.py
onegov/agency/layouts/people.py
onegov/agency/locale/de_CH/LC_MESSAGES/onegov.agency.po
onegov/agency/models/__init__.py
onegov/agency/models/agency.py
onegov/agency/models/membership.py
onegov/agency/models/move.py
onegov/agency/models/person.py
onegov/agency/models/ticket.py
onegov/agency/static/logos/canton-ar.svg
onegov/agency/static/logos/canton-zg-bw.svg
onegov/agency/templates/agencies.pt
onegov/agency/templates/agency.pt
onegov/agency/templates/extended_people.pt
onegov/agency/templates/hidden.pt
onegov/agency/templates/macros.pt
onegov/agency/templates/membership.pt
onegov/agency/templates/person.pt
onegov/agency/tests/conftest.py
onegov/agency/tests/test_app.py
onegov/agency/tests/test_cli.py
onegov/agency/tests/test_collections.py
onegov/agency/tests/test_forms.py
onegov/agency/tests/test_initial_content.py
onegov/agency/tests/test_layouts.py
onegov/agency/tests/test_models.py
onegov/agency/tests/test_pdf.py
onegov/agency/tests/test_views.py
onegov/agency/tests/fixtures/export-pdf.xls
onegov/agency/tests/fixtures/export.xls
onegov/agency/tests/fixtures/organigram.png
onegov/agency/theme/__init__.py
onegov/agency/theme/agency_theme.py
onegov/agency/theme/styles/agency.scss
onegov/agency/theme/styles/chosen.scss
onegov/agency/theme/styles/people.scss
onegov.agency-1.12.0.dist-info/METADATA
onegov.agency-1.12.0.dist-info/WHEEL
onegov.agency-1.12.0.dist-info/entry_points.txt
onegov.agency-1.12.0.dist-info/namespace_packages.txt
onegov.agency-1.12.0.dist-info/top_level.txt
onegov.agency-1.12.0.dist-info/RECORD
