Metadata-Version: 2.1
Name: onegov.agency
Version: 1.12.0
Summary: Administrative units and relationships for administrative directories.
Home-page: http://github.com/onegov/onegov.agency
Author: Seantis GmbH
Author-email: info@seantis.ch
License: GPLv2
Platform: any
Classifier: Intended Audience :: Developers
Classifier: Programming Language :: Python :: 3 :: Only
Classifier: Programming Language :: Python :: 3.6
Classifier: Programming Language :: Python :: 3.7
Classifier: Topic :: Software Development :: Libraries :: Python Modules
Classifier: License :: OSI Approved :: GNU General Public License v2 (GPLv2)
Requires-Python: >=3.6
Requires-Dist: cached-property
Requires-Dist: bleach
Requires-Dist: html5lib
Requires-Dist: onegov.core
Requires-Dist: onegov.form
Requires-Dist: onegov.file
Requires-Dist: onegov.org (>=1.1.10)
Requires-Dist: onegov.people (>=0.10.0)
Requires-Dist: onegov.pdf (>=0.4.0)
Requires-Dist: pyyaml
Requires-Dist: xlrd
Provides-Extra: test
Requires-Dist: coverage ; extra == 'test'
Requires-Dist: freezegun ; extra == 'test'
Requires-Dist: mock ; extra == 'test'
Requires-Dist: onegov-testing ; extra == 'test'
Requires-Dist: pyquery ; extra == 'test'
Requires-Dist: PyPDF2 ; extra == 'test'
Requires-Dist: pytest-localserver ; extra == 'test'
Requires-Dist: pytest (>=3.0.0) ; extra == 'test'
Requires-Dist: webtest ; extra == 'test'
